pyqt_color_button/__init__.py
pyqt_color_button/colorButton.py
pyqt_color_button-0.0.1.dist-info/LICENSE
pyqt_color_button-0.0.1.dist-info/METADATA
pyqt_color_button-0.0.1.dist-info/WHEEL
pyqt_color_button-0.0.1.dist-info/top_level.txt
pyqt_color_button-0.0.1.dist-info/RECORD
