Metadata-Version: 2.1
Name: pyqt-color-button
Version: 0.0.1
Summary: circle-shaped color button
Home-page: https://github.com/yjg30737/pyqt-color-button.git
Author: Jung Gyu Yoon
Author-email: yjg30737@gmail.com
License: MIT
Platform: UNKNOWN
License-File: LICENSE
Requires-Dist: PyQt5 (>=5.8)
